
[
    {
        "end": "11.810",
        "speaker_id": "SPEAKER_01",
        "start": "0.031",
        "transcriptions": [
            {
                "end": 0.82,
                "start": 0.0,
                "word": " I'm"
            },
            {
                "end": 1.32,
                "start": 0.82,
                "word": " testing"
            },
            {
                "end": 1.88,
                "start": 1.32,
                "word": " this"
            },
            {
                "end": 2.5,
                "start": 1.88,
                "word": " is"
            },
            {
                "end": 2.76,
                "start": 2.5,
                "word": " just"
            },
            {
                "end": 3.04,
                "start": 2.76,
                "word": " a"
            },
            {
                "end": 3.54,
                "start": 3.04,
                "word": " recording"
            },
            {
                "end": 4.08,
                "start": 3.54,
                "word": " for"
            },
            {
                "end": 4.66,
                "start": 4.08,
                "word": " testing"
            },
            {
                "end": 4.98,
                "start": 4.66,
                "word": " by"
            },
            {
                "end": 5.34,
                "start": 4.98,
                "word": " note"
            },
            {
                "end": 6.22,
                "start": 5.34,
                "word": " transcript"
            },
            {
                "end": 7.16,
                "start": 6.22,
                "word": " now"
            },
            {
                "end": 7.3,
                "start": 7.16,
                "word": " I'm"
            },
            {
                "end": 7.44,
                "start": 7.3,
                "word": " gonna"
            },
            {
                "end": 7.68,
                "start": 7.44,
                "word": " switch"
            },
            {
                "end": 7.94,
                "start": 7.68,
                "word": " to"
            },
            {
                "end": 8.04,
                "start": 7.94,
                "word": " a"
            },
            {
                "end": 8.26,
                "start": 8.04,
                "word": " different"
            },
            {
                "end": 8.64,
                "start": 8.26,
                "word": " voice"
            },
            {
                "end": 8.9,
                "start": 8.64,
                "word": " and"
            },
            {
                "end": 9.22,
                "start": 8.9,
                "word": " hopefully"
            },
            {
                "end": 9.6,
                "start": 9.22,
                "word": " it's"
            },
            {
                "end": 9.8,
                "start": 9.6,
                "word": " going"
            },
            {
                "end": 10.24,
                "start": 9.8,
                "word": " to"
            },
            {
                "end": 11.32,
                "start": 10.24,
                "word": " transcript"
            },
            {
                "end": 11.74,
                "start": 11.32,
                "word": " it"
            }
        ]
    },
    {
        "end": "13.970",
        "speaker_id": "SPEAKER_00",
        "start": "13.160",
        "transcriptions": [
            {
                "end": 0.3,
                "start": 0.0,
                "word": " Hello."
            }
        ]
    },
    {
        "end": "19.977",
        "speaker_id": "SPEAKER_01",
        "start": "14.932",
        "transcriptions": [
            {
                "end": 0.38,
                "start": 0.0,
                "word": " One,"
            },
            {
                "end": 1.1,
                "start": 0.7,
                "word": " two,"
            },
            {
                "end": 1.52,
                "start": 1.3,
                "word": " three,"
            },
            {
                "end": 2.1,
                "start": 1.76,
                "word": " desk,"
            },
            {
                "end": 3.1,
                "start": 2.58,
                "word": " desk."
            },
            {
                "end": 4.26,
                "start": 3.54,
                "word": " Testing."
            }
        ]
    }
]